mmdet_taeuk4958/__init__.py
mmdet_taeuk4958/version.py
mmdet_taeuk4958/apis/__init__.py
mmdet_taeuk4958/apis/inference.py
mmdet_taeuk4958/apis/test.py
mmdet_taeuk4958/apis/train.py
mmdet_taeuk4958/core/__init__.py
mmdet_taeuk4958/core/anchor/__init__.py
mmdet_taeuk4958/core/anchor/anchor_generator.py
mmdet_taeuk4958/core/anchor/builder.py
mmdet_taeuk4958/core/anchor/point_generator.py
mmdet_taeuk4958/core/anchor/utils.py
mmdet_taeuk4958/core/bbox/__init__.py
mmdet_taeuk4958/core/bbox/builder.py
mmdet_taeuk4958/core/bbox/demodata.py
mmdet_taeuk4958/core/bbox/transforms.py
mmdet_taeuk4958/core/bbox/assigners/__init__.py
mmdet_taeuk4958/core/bbox/assigners/approx_max_iou_assigner.py
mmdet_taeuk4958/core/bbox/assigners/assign_result.py
mmdet_taeuk4958/core/bbox/assigners/atss_assigner.py
mmdet_taeuk4958/core/bbox/assigners/base_assigner.py
mmdet_taeuk4958/core/bbox/assigners/center_region_assigner.py
mmdet_taeuk4958/core/bbox/assigners/grid_assigner.py
mmdet_taeuk4958/core/bbox/assigners/hungarian_assigner.py
mmdet_taeuk4958/core/bbox/assigners/mask_hungarian_assigner.py
mmdet_taeuk4958/core/bbox/assigners/max_iou_assigner.py
mmdet_taeuk4958/core/bbox/assigners/point_assigner.py
mmdet_taeuk4958/core/bbox/assigners/region_assigner.py
mmdet_taeuk4958/core/bbox/assigners/sim_ota_assigner.py
mmdet_taeuk4958/core/bbox/assigners/task_aligned_assigner.py
mmdet_taeuk4958/core/bbox/assigners/uniform_assigner.py
mmdet_taeuk4958/core/bbox/coder/__init__.py
mmdet_taeuk4958/core/bbox/coder/base_bbox_coder.py
mmdet_taeuk4958/core/bbox/coder/bucketing_bbox_coder.py
mmdet_taeuk4958/core/bbox/coder/delta_xywh_bbox_coder.py
mmdet_taeuk4958/core/bbox/coder/distance_point_bbox_coder.py
mmdet_taeuk4958/core/bbox/coder/legacy_delta_xywh_bbox_coder.py
mmdet_taeuk4958/core/bbox/coder/pseudo_bbox_coder.py
mmdet_taeuk4958/core/bbox/coder/tblr_bbox_coder.py
mmdet_taeuk4958/core/bbox/coder/yolo_bbox_coder.py
mmdet_taeuk4958/core/bbox/iou_calculators/__init__.py
mmdet_taeuk4958-1.0.9.dist-info/METADATA
mmdet_taeuk4958-1.0.9.dist-info/WHEEL
mmdet_taeuk4958-1.0.9.dist-info/top_level.txt
mmdet_taeuk4958-1.0.9.dist-info/RECORD
