Metadata-Version: 2.1
Name: mmdet-taeuk4958
Version: 1.0.9
Summary: OpenMMLab Detection Toolbox and Benchmark (costomized by taeuk4958 for personal project)
Home-page: https://github.com/open-mmlab/mmdetection (costomized by https://github.com/HibernationNo1/project_4_kubeflow_pipeline.git)
Author: MMDetection Contributors (costomized by taeuk4958) 
Author-email: openmmlab@gmail.com (costomized by taeuk4958@gmail.com)
License: Apache License 2.0
Platform: UNKNOWN
Classifier: Development Status :: 5 - Production/Stable
Classifier: License :: OSI Approved :: Apache Software License
Classifier: Operating System :: OS Independent
Classifier: Programming Language :: Python :: 3
Classifier: Programming Language :: Python :: 3.6
Classifier: Programming Language :: Python :: 3.7
Classifier: Programming Language :: Python :: 3.8
Classifier: Programming Language :: Python :: 3.9
Requires-Dist: matplotlib
Requires-Dist: numpy
Requires-Dist: pycocotools
Requires-Dist: six
Requires-Dist: terminaltables
Provides-Extra: all
Provides-Extra: build
Requires-Dist: cython ; extra == 'build'
Requires-Dist: numpy ; extra == 'build'
Provides-Extra: optional
Requires-Dist: cityscapesscripts ; extra == 'optional'
Requires-Dist: imagecorruptions ; extra == 'optional'
Requires-Dist: scipy ; extra == 'optional'
Requires-Dist: sklearn ; extra == 'optional'
Requires-Dist: timm ; extra == 'optional'
Provides-Extra: tests
Requires-Dist: asynctest ; extra == 'tests'
Requires-Dist: codecov ; extra == 'tests'
Requires-Dist: flake8 ; extra == 'tests'
Requires-Dist: interrogate ; extra == 'tests'
Requires-Dist: isort (==4.3.21) ; extra == 'tests'
Requires-Dist: kwarray ; extra == 'tests'
Requires-Dist: mmtrack ; extra == 'tests'
Requires-Dist: onnx (==1.7.0) ; extra == 'tests'
Requires-Dist: onnxruntime (>=1.8.0) ; extra == 'tests'
Requires-Dist: protobuf (<=3.20.1) ; extra == 'tests'
Requires-Dist: pytest ; extra == 'tests'
Requires-Dist: ubelt ; extra == 'tests'
Requires-Dist: xdoctest (>=0.10.0) ; extra == 'tests'
Requires-Dist: yapf ; extra == 'tests'
